{"id": "Generator", "path": "/home/hendrik/Programming/Python/BA/Simulation/Generator.py", "mtime": 1594557187, "size": 1543, "hash": "152fe6f01da66619c3c4414e6d197123", "data_mtime": 1594557353, "dependencies": ["Simulation", "typing", "random", "builtins"], "suppressed": [], "child_modules": [], "options": {"ignore_missing_imports": false, "strict_boolean": false, "ignore_errors": false, "strict_optional_whitelist": null, "disallow_untyped_calls": false, "check_untyped_defs": false, "platform": "linux", "disallow_any_unimported": false, "follow_imports": "normal", "disallow_untyped_decorators": false, "warn_no_return": true, "quick_and_dirty": false, "show_none_errors": true, "disallow_any_generics": false, "no_implicit_optional": false, "strict_optional": false, "warn_return_any": false, "disallow_subclassing_any": false, "disallow_any_decorated": false, "disallow_any_expr": false, "disallow_any_explicit": false, "disallow_untyped_defs": false}, "dep_prios": [10, 5, 10, 5], "interface_hash": "96a7cf22d5dd13831eca898ca7f30940", "version_id": "0.560", "ignore_all": false}
